Metadata-Version: 2.1
Name: odoo14-addon-stock_picking_line_sequence
Version: 14.0.1.0.1.dev10
Summary: Manages the order of stock moves by displaying its sequence
Home-page: https://github.com/OCA/stock-logistics-workflow
Author: Camptocamp, Eficent, Serpent CS, Odoo Community Association (OCA), ArcheTI
Author-email: support@odoo-community.org
License: AGPL-3
Classifier: Programming Language :: Python
Classifier: Framework :: Odoo
Classifier: Framework :: Odoo :: 14.0
Classifier: License :: OSI Approved :: GNU Affero General Public License v3
Requires-Python: >=3.6
Requires-Dist: odoo<14.1dev,>=14.0a
